get_variable_name/__init__.py
get_variable_name/get_variable_name.py
get_variable_name-0.0.2.dist-info/DESCRIPTION.rst
get_variable_name-0.0.2.dist-info/METADATA
get_variable_name-0.0.2.dist-info/RECORD
get_variable_name-0.0.2.dist-info/WHEEL
get_variable_name-0.0.2.dist-info/metadata.json
get_variable_name-0.0.2.dist-info/top_level.txt
