Metadata-Version: 2.0
Name: get-variable-name
Version: 0.0.2
Summary: Returns variable name as a string
Home-page: https://github.com/sorxcode/get-variable-name
Author: Farinnako Adeyanju Victor
Author-email: ennythan006@gmail.com
License: UNKNOWN
Platform: UNKNOWN
Classifier: Programming Language :: Python
Classifier: License :: OSI Approved :: MIT License
Classifier: Operating System :: OS Independent
